wheel_getter/__init__.py
wheel_getter/actions.py
wheel_getter/cache.py
wheel_getter/checksums.py
wheel_getter/copyfiles.py
wheel_getter/main.py
wheel_getter/pkgstatus.py
wheel_getter/reporter.py
wheel_getter-0.6.6.dist-info/licenses/LICENSE
wheel_getter-0.6.6.dist-info/WHEEL
wheel_getter-0.6.6.dist-info/entry_points.txt
wheel_getter-0.6.6.dist-info/METADATA
wheel_getter-0.6.6.dist-info/RECORD
