Metadata-Version: 2.4
Name: wheel-getter
Version: 0.6.6
Summary: Get or build wheels for isolated installation of a Python package
Keywords: wheel,installation,package,uv
Author: Detlef Lannert
Author-email: Detlef Lannert <detlef@lannert.de>
License-File: LICENSE
Classifier: Development Status :: 4 - Beta
Classifier: Intended Audience :: Developers
Classifier: Programming Language :: Python :: 3
Classifier: Programming Language :: Python :: 3.12
Classifier: Programming Language :: Python :: 3.13
Classifier: Programming Language :: Python :: 3.14
Classifier: Topic :: Software Development :: Build Tools
Classifier: Topic :: System :: Installation/Setup
Classifier: Topic :: Utilities
Classifier: Typing :: Typed
Requires-Dist: cyclopts>=3.23.1
Requires-Dist: msgspec>=0.19.0
Requires-Dist: niquests>=3.15.2
Requires-Dist: pip>=25.2
Requires-Dist: wheel-filename>=1.4.2
Requires-Dist: xdg-base-dirs>=6.0.2
Requires-Python: >=3.12
Project-URL: Changelog, https://github.com/detlefla/wheel-getter/blob/master/CHANGELOG.md
Project-URL: Homepage, https://github.com/detlefla/wheel-getter
Project-URL: Issues, https://github.com/detlefla/wheel-getter/issues
Project-URL: Repository, https://github.com/detlefla/wheel-getter.git
